serde_xyz-0.2.0.dist-info/METADATA
serde_xyz-0.2.0.dist-info/WHEEL
serde_xyz/__init__.py
serde_xyz/serde_xyz.cpython-313-darwin.so
serde_xyz-0.2.0.dist-info/RECORD
