Metadata-Version: 2.4
Name: serde_xyz
Version: 0.2.0
Summary: Serialize and deserialize molecular structure .xyz files.
Requires-Python: >=3
